spyc_spc/__init__.py
spyc_spc/helpers/__init__.py
spyc_spc/helpers/partnumber.py
spyc_spc/helpers/spcfigure.py
spyc_spc/main.py
spyc_spc/plot_options.json
spyc_spc-1.1.dist-info/entry_points.txt
spyc_spc-1.1.dist-info/LICENSE
spyc_spc-1.1.dist-info/WHEEL
spyc_spc-1.1.dist-info/METADATA
spyc_spc-1.1.dist-info/RECORD
