Metadata-Version: 2.1
Name: spyc-spc
Version: 1.1
Summary: Simple tool to help plot SPC data from multiple locations for comparison
Home-page: https://github.com/fanoway/spyc
Author: fanoway
Author-email: 86997883+fanoway@users.noreply.github.com
Requires-Python: >=3.8,<4.0
Classifier: Programming Language :: Python :: 3
Classifier: Programming Language :: Python :: 3.8
Classifier: Programming Language :: Python :: 3.9
Requires-Dist: cheroot (>=8.5.2,<9.0.0)
Requires-Dist: dash (>=1.20.0,<2.0.0)
Requires-Dist: docopt (>=0.6.2,<0.7.0)
Requires-Dist: ipywidgets (>=7.6.3,<8.0.0)
Requires-Dist: mainentry (>=2.0,<3.0)
Requires-Dist: numpy (>=1.21.0,<2.0.0)
Requires-Dist: openpyxl (>=3.0.7,<4.0.0)
Requires-Dist: pandas (>=1.3.0,<2.0.0)
Requires-Dist: plotly (>=5.1.0,<6.0.0)
